kelvin_app-6.1.0-py3.8-nspkg.pth
kelvin/app/__init__.py
kelvin/app/__main__.py
kelvin/app/application.py
kelvin/app/common.py
kelvin/app/config.py
kelvin/app/context.py
kelvin/app/data.py
kelvin/app/injector.py
kelvin/app/logs.py
kelvin/app/mapping_proxy.py
kelvin/app/py.typed
kelvin/app/server.py
kelvin/app/utils.py
kelvin/app/version.py
kelvin/app/cli/__init__.py
kelvin/app/cli/main.py
kelvin/app/cli/run.py
kelvin/app/client/__init__.py
kelvin/app/client/client.py
kelvin/app/client/config.py
kelvin/app/client/connection.py
kelvin/app/client/exception.py
kelvin/app/client/request.py
kelvin/app/client/response.py
kelvin/app/client/run.py
kelvin/app/client/state.py
kelvin/core/context.py
kelvin/core/application/__init__.py
kelvin/core/application/application.py
kelvin/core/application/data.py
kelvin/core/application/poller.py
kelvin/core/utils/__init__.py
kelvin/sdk/extractor/__init__.py
kelvin/sdk/extractor/config.py
kelvin/sdk/extractor/extractor.py
kelvin/sdk/extractor/extractor.yaml
kelvin/sdk/injector/__init__.py
kelvin/sdk/injector/config.py
kelvin/sdk/injector/injector.py
kelvin/sdk/injector/injector.yaml
kelvin_app-6.1.0.dist-info/LICENSE.rst
kelvin_app-6.1.0.dist-info/METADATA
kelvin_app-6.1.0.dist-info/WHEEL
kelvin_app-6.1.0.dist-info/entry_points.txt
kelvin_app-6.1.0.dist-info/namespace_packages.txt
kelvin_app-6.1.0.dist-info/top_level.txt
kelvin_app-6.1.0.dist-info/RECORD
