Metadata-Version: 2.1
Name: kelvin-app
Version: 6.1.0
Summary: Kelvin Application Framework
Home-page: https://kelvininc.com/
Author: Kelvin Inc
Author-email: engineering@kelvininc.com
License: UNKNOWN
Platform: any
Classifier: Operating System :: OS Independent
Classifier: Programming Language :: Python :: 3.7
Classifier: Programming Language :: Python :: 3.8
Classifier: Programming Language :: Python :: 3.9
Requires-Python: <3.10,>=3.7.0
License-File: LICENSE.rst
Requires-Dist: click (==7.1.2)
Requires-Dist: click-shell (==2.0)
Requires-Dist: colorama (==0.4.*)
Requires-Dist: kelvin-icd (==6.1.0)
Requires-Dist: kelvin-sdk-client (==6.1.0)
Requires-Dist: packaging (==20.9)
Requires-Dist: pydantic[email] (==1.7.*)
Requires-Dist: PyYAML (==5.4.*)
Requires-Dist: pyzmq (==22.0.*)
Requires-Dist: structlog (==20.2.*)
Requires-Dist: xdg (==5.0.*)
Requires-Dist: importlib-metadata ; python_version < "3.8"
Requires-Dist: typing-extensions ; python_version < "3.8"
Provides-Extra: data
Requires-Dist: pyarrow (==4.0.*) ; extra == 'data'
Requires-Dist: pandas (<1.3,>=1.0.0) ; extra == 'data'
Provides-Extra: development
Requires-Dist: pre-commit ; extra == 'development'
Provides-Extra: docs
Requires-Dist: Sphinx ; extra == 'docs'
Requires-Dist: sphinx-autodoc-typehints ; extra == 'docs'
Requires-Dist: sphinx-rtd-theme ; extra == 'docs'
Requires-Dist: ipython ; extra == 'docs'
Provides-Extra: format
Requires-Dist: isort (==5.7.*) ; extra == 'format'
Requires-Dist: black (==20.8b1) ; extra == 'format'
Provides-Extra: lint
Requires-Dist: flake8 (==3.8.*) ; extra == 'lint'
Requires-Dist: flake8-print (==4.0.*) ; extra == 'lint'
Requires-Dist: flake8-isort (==4.0.*) ; extra == 'lint'
Requires-Dist: pep8-naming (==0.11.*) ; extra == 'lint'
Requires-Dist: mypy (==0.902) ; extra == 'lint'
Requires-Dist: lxml (==4.6.3) ; extra == 'lint'
Requires-Dist: types-click (==7.1.*) ; extra == 'lint'
Requires-Dist: types-PyYAML (==5.4.*) ; extra == 'lint'
Requires-Dist: types-pkg-resources (==0.1.*) ; extra == 'lint'
Provides-Extra: security
Requires-Dist: bandit (==1.7.*) ; extra == 'security'
Requires-Dist: safety (==1.10.*) ; extra == 'security'
Provides-Extra: tests
Requires-Dist: pandas (<1.3,>=1.0.0) ; extra == 'tests'
Requires-Dist: pyarrow (>=3.0.*) ; extra == 'tests'
Requires-Dist: ipython ; extra == 'tests'
Requires-Dist: kelvin-icd[builder] (==6.1.0) ; extra == 'tests'
Requires-Dist: pytest (>=6.0.1) ; extra == 'tests'
Requires-Dist: pytest-asyncio (==0.14.0) ; extra == 'tests'
Requires-Dist: pytest-cov (==2.8.1) ; extra == 'tests'
Requires-Dist: pytest-mock (==3.1.0) ; extra == 'tests'
Requires-Dist: pytest-benchmark (==3.2.3) ; extra == 'tests'
Requires-Dist: pytest-codestyle (==2.0.1) ; extra == 'tests'
Requires-Dist: pytest-flakes (==4.0.0) ; extra == 'tests'
Requires-Dist: pytest-html (==2.1.1) ; extra == 'tests'
Requires-Dist: pytest-mypy (==0.6.1) ; extra == 'tests'
Requires-Dist: pytest-timeout (==1.3.4) ; extra == 'tests'
Requires-Dist: pytest-xdist (==1.32.0) ; extra == 'tests'
Requires-Dist: pytest-virtualenv (==1.7.0) ; extra == 'tests'
Requires-Dist: requests-mock (==1.8.0) ; extra == 'tests'
Requires-Dist: coverage (>=5.3) ; extra == 'tests'
Requires-Dist: pyrobuf (==0.9.*) ; extra == 'tests'
Provides-Extra: wheel
Requires-Dist: wheel ; extra == 'wheel'
Requires-Dist: twine ; extra == 'wheel'
